tests/__init__.py
tests/conftest.py
tests/test_examples.py
trafficbench/__init__.py
trafficbench/_lognplot_client.py
trafficbench/airtime.py
trafficbench/checksum.py
trafficbench/cli.py
trafficbench/cli_extract.py
trafficbench/cli_proto.py
trafficbench/cli_serial_uart.py
trafficbench/cli_trx_analyze.py
trafficbench/cli_trx_dump.py
trafficbench/constants.py
trafficbench/crc.py
trafficbench/file_database.py
trafficbench/filesystem.py
trafficbench/glue_config.py
trafficbench/logger.py
trafficbench/rssi.py
trafficbench/table_records.py
trafficbench/unit_conversion.py
trafficbench-0.2.2.dist-info/LICENSE
trafficbench-0.2.2.dist-info/METADATA
trafficbench-0.2.2.dist-info/WHEEL
trafficbench-0.2.2.dist-info/entry_points.txt
trafficbench-0.2.2.dist-info/top_level.txt
trafficbench-0.2.2.dist-info/zip-safe
trafficbench-0.2.2.dist-info/RECORD
