Metadata-Version: 2.2
Name: trafficbench
Version: 0.2.2
Summary: a tool suite for the experimental exploration of concurrent packet transmissions and their consequences (physical layer effects) in low-power wireless networks
Author: Ingmar Splitt
Author-email: Carsten Herrmann <carsten.herrmann@tu-dresden.de>
Maintainer-email: ingmar.splitt@tu-dresden.de
Project-URL: Homepage, https://pypi.org/project/trafficbench/
Project-URL: Tracker, https://github.com/orgua/trafficbench/issues
Project-URL: Source, https://github.com/orgua/trafficbench
Keywords: concurrent transmission,physical layer,low-power,wireless,rssi,scheduling,synchronization
Platform: unix
Platform: linux
Platform: osx
Platform: cygwin
Platform: win32
Platform: win64
Classifier: Development Status :: 5 - Production/Stable
Classifier: Intended Audience :: Developers
Classifier: Intended Audience :: Information Technology
Classifier: Intended Audience :: Science/Research
Classifier: Programming Language :: Python :: 3.8
Classifier: Programming Language :: Python :: 3.9
Classifier: Programming Language :: Python :: 3.10
Classifier: Programming Language :: Python :: 3.11
Classifier: Programming Language :: Python :: 3.12
Classifier: Programming Language :: Python :: 3.13
Classifier: Operating System :: OS Independent
Classifier: Natural Language :: English
Requires-Python: >=3.8
License-File: LICENSE
Requires-Dist: numpy<2.0.0
Requires-Dist: tables
Requires-Dist: cbor2<5.5.0
Requires-Dist: crcmod
Requires-Dist: chromalog
Requires-Dist: pyserial
Requires-Dist: typing-extensions
Requires-Dist: typer
Provides-Extra: glue
Requires-Dist: glue-core; extra == "glue"
Requires-Dist: glueviz; extra == "glue"
Requires-Dist: matplotlib; extra == "glue"
Provides-Extra: lognplot
Requires-Dist: lognplot; extra == "lognplot"
Provides-Extra: dev
Requires-Dist: twine; extra == "dev"
Requires-Dist: pre-commit; extra == "dev"
Requires-Dist: pyright; extra == "dev"
Provides-Extra: test
Requires-Dist: pytest; extra == "test"
Requires-Dist: coverage; extra == "test"
Requires-Dist: shepherd-core[elf]; extra == "test"
